{
  "izbori" : "Lokalni izbori 2025",
  "datum" : "09.05.2025.",
  "vrijeme" : "11:15",
  "izboriOznaka" : "08",
  "zupSifra" : "02",
  "gropSifra" : "3522",
  "bmSifra" : "005",
  "zupNaziv" : "KRAPINSKO-ZAGORSKA ŽUPANIJA",
  "gropNaziv" : "PREGRADA",
  "bmNaziv" : "KOSTEL",
  "bmZatvoreno" : 0,
  "bmUkupno" : 0,
  "biraciUkupno" : 0,
  "biraciGlasovalo" : 0,
  "biraciGlasovaloPosto" : "0,00",
  "listiciUkupno" : 0,
  "listiciVazeci" : 0,
  "listiciVazeciPosto" : "0,00",
  "listiciNevazeci" : 0,
  "listiciNevazeciPosto" : "0,00",
  "napomena" : "",
  "lista" : [ {
    "rbr" : 1,
    "stranke" : "KANDIDACIJSKA LISTA GRUPE BIRAČA",
    "strankePuniNaziv" : [ {
      "naziv" : "KANDIDACIJSKA LISTA GRUPE BIRAČA"
    } ],
    "naziv" : "STJEPAN MIKLAUŽIĆ - nositelj kandidacijske liste",
    "nazivDodatno" : "",
    "zamjenici" : [ ],
    "jedinstvenaSifra" : "2636",
    "glasova" : 0,
    "posto" : "0,00",
    "bmUkupno" : 0,
    "bmZatvoreno" : 0,
    "bmObradjeno" : 0,
    "biraciGlasovalo" : 0,
    "biraciUkupno" : 0,
    "listiciVazeci" : 0,
    "listiciUkupno" : 0,
    "listiciNevazeci" : 0,
    "biraciGlasovaloPosto" : "0,00",
    "listiciVazeciPosto" : "0,00",
    "listiciNevazeciPosto" : "0,00",
    "bmObradjenoPosto" : "0,00"
  }, {
    "rbr" : 2,
    "stranke" : "HDZ, DHSS, HSU",
    "strankePuniNaziv" : [ {
      "naziv" : "HRVATSKA DEMOKRATSKA ZAJEDNICA - HDZ"
    }, {
      "naziv" : "DEMOKRATSKI HSS - DHSS"
    }, {
      "naziv" : "HRVATSKA STRANKA UMIROVLJENIKA - HSU"
    } ],
    "naziv" : "GORAN VUKMANIĆ - nositelj kandidacijske liste",
    "nazivDodatno" : "",
    "zamjenici" : [ ],
    "jedinstvenaSifra" : "003023283",
    "glasova" : 0,
    "posto" : "0,00",
    "bmUkupno" : 0,
    "bmZatvoreno" : 0,
    "bmObradjeno" : 0,
    "biraciGlasovalo" : 0,
    "biraciUkupno" : 0,
    "listiciVazeci" : 0,
    "listiciUkupno" : 0,
    "listiciNevazeci" : 0,
    "biraciGlasovaloPosto" : "0,00",
    "listiciVazeciPosto" : "0,00",
    "listiciNevazeciPosto" : "0,00",
    "bmObradjenoPosto" : "0,00"
  }, {
    "rbr" : 3,
    "stranke" : "SDP, HSS",
    "strankePuniNaziv" : [ {
      "naziv" : "SOCIJALDEMOKRATSKA PARTIJA HRVATSKE - SDP"
    }, {
      "naziv" : "HRVATSKA SELJAČKA STRANKA - HSS"
    } ],
    "naziv" : "DAVORKA FILIPČIĆ - nositeljica kandidacijske liste",
    "nazivDodatno" : "",
    "zamjenici" : [ ],
    "jedinstvenaSifra" : "004017",
    "glasova" : 0,
    "posto" : "0,00",
    "bmUkupno" : 0,
    "bmZatvoreno" : 0,
    "bmObradjeno" : 0,
    "biraciGlasovalo" : 0,
    "biraciUkupno" : 0,
    "listiciVazeci" : 0,
    "listiciUkupno" : 0,
    "listiciNevazeci" : 0,
    "biraciGlasovaloPosto" : "0,00",
    "listiciVazeciPosto" : "0,00",
    "listiciNevazeciPosto" : "0,00",
    "bmObradjenoPosto" : "0,00"
  } ],
  "bmObradjeno" : 0,
  "glasova" : 0,
  "bmObradjenoPosto" : "0,00",
  "posto" : "0,0"
}